treadSRCNN/__init__.py
treadSRCNN/treadSRCNN.py
treadSRCNN-0.1.4.dist-info/LICENSE
treadSRCNN-0.1.4.dist-info/METADATA
treadSRCNN-0.1.4.dist-info/WHEEL
treadSRCNN-0.1.4.dist-info/top_level.txt
treadSRCNN-0.1.4.dist-info/RECORD
