Metadata-Version: 2.1
Name: treadSRCNN
Version: 0.1.4
Summary: SRCNN implementation for upsampling grayscale images of tire treads.
Home-page: https://github.com/bohundan/treadscan-SRCNN
Author: Daniel Bohuněk
Author-email: bohundan@fit.cvut.cz
Project-URL: Bug Tracker, https://github.com/bohundan/treadscan-SRCNN/issues
Classifier: Programming Language :: Python :: 3
Classifier: License :: OSI Approved :: MIT License
Classifier: Operating System :: OS Independent
Requires-Python: >=3.8
License-File: LICENSE
Requires-Dist: numpy
Requires-Dist: opencv-python
Requires-Dist: opencv-contrib-python
Requires-Dist: torch
Requires-Dist: torchvision
